LICENSE
README.md
setup.py
src/sally/__init__.py
src/sally/app/__init__.py
src/sally/app/bootstrapping.py
src/sally/app/logs.py
src/sally/app/cli/__init__.py
src/sally/app/cli/kli.py
src/sally/app/cli/commands/__init__.py
src/sally/app/cli/commands/version.py
src/sally/app/cli/commands/hook/__init__.py
src/sally/app/cli/commands/hook/demo.py
src/sally/app/cli/commands/server/__init__.py
src/sally/app/cli/commands/server/start.py
src/sally/core/__init__.py
src/sally/core/basing.py
src/sally/core/credentials.py
src/sally/core/handling.py
src/sally/core/httping.py
src/sally/core/monitoring.py
src/sally/core/serving.py
src/sally/core/verifying.py
src/sally_verifier.egg-info/PKG-INFO
src/sally_verifier.egg-info/SOURCES.txt
src/sally_verifier.egg-info/dependency_links.txt
src/sally_verifier.egg-info/entry_points.txt
src/sally_verifier.egg-info/not-zip-safe
src/sally_verifier.egg-info/requires.txt
src/sally_verifier.egg-info/top_level.txt