Metadata-Version: 2.1
Name: sally-verifier
Version: 1.0.3
Summary: vLEI Audit Reporting API
Home-page: https://github.com/GLEIF-IT/sally
Author: Philip S. Feairheller
Author-email: pfeairheller@gmail.com
License: Apache-2.0
Project-URL: Documentation, https://sally.readthedocs.io/
Project-URL: Changelog, https://sally.readthedocs.io/en/latest/changelog.html
Project-URL: Issue Tracker, https://github.com/WebOfTrust/sally/issues
Classifier: Development Status :: 3 - Alpha
Classifier: Intended Audience :: Developers
Classifier: Operating System :: Unix
Classifier: Operating System :: POSIX
Classifier: Operating System :: Microsoft :: Windows
Classifier: Programming Language :: Python :: 3.12
Classifier: Programming Language :: Python :: Implementation :: CPython
Classifier: Topic :: Utilities
Requires-Python: >=3.12.3
Provides-Extra: test
Provides-Extra: docs
License-File: LICENSE
